COPYING
MANIFEST.in
README.md
requirements.txt
setup.py
druid_cli/__init__.py
druid_cli/cli.py
druid_cli/decorators.py
druid_cli/druid.py
druid_cli/errors.py
druid_cli/tasks.py
druid_cli/types.py
druid_cli.egg-info/PKG-INFO
druid_cli.egg-info/SOURCES.txt
druid_cli.egg-info/dependency_links.txt
druid_cli.egg-info/entry_points.txt
druid_cli.egg-info/not-zip-safe
druid_cli.egg-info/requires.txt
druid_cli.egg-info/top_level.txt