Metadata-Version: 1.1
Name: druid-cli
Version: 0.3.1
Summary: Missing command line interface to druid data store.
Home-page: https://github.com/swistakm/druid-cli
Author: Michał Jaworski
Author-email: swistakm@gmail.com
License: LGPL
Platform: UNKNOWN
Classifier: Development Status :: 4 - Beta
Classifier: Intended Audience :: Developers
Classifier: Operating System :: OS Independent
Classifier: Programming Language :: Python
Classifier: Programming Language :: Python :: 3
Classifier: License :: OSI Approved :: GNU Lesser General Public License v3 or later (LGPLv3+)
